Metadata-Version: 2.1
Name: tracktry
Version: 0.1.1
Summary: UNKNOWN
Home-page: https://github.com/slinkymanbyday/tracktry
Author: slinkymanbyday
Author-email: slinkymanbyday@gmail.com
License: UNKNOWN
Platform: UNKNOWN
Classifier: Programming Language :: Python :: 3
Classifier: License :: OSI Approved :: MIT License
Classifier: Operating System :: OS Independent
